newsstand_db
