Metadata-Version: 1.1
Name: newsstand-db
Version: 0.5.1
Summary: Create, search and analyze a DB with your Apple's newsstand app information
Home-page: https://github.com/jorgeblanco/newsstand_db
Author: Jorge Blanco
Author-email: py@jorgeblan.co
License: GPLv2
Keywords: apple newsstand ios analytics database db
Platform: UNKNOWN
Classifier: Development Status :: 4 - Beta
Classifier: License :: OSI Approved :: GNU General Public License v2 (GPLv2)
Classifier: Programming Language :: Python :: 2.7
Classifier: Topic :: Office/Business :: Financial
